{
  "@id": "https://api.nuget.org/v3/catalog0/data/2018.11.19.18.32.04/sharpmigrations.2.0.0-beta3.json",
  "@type": [
    "PackageDetails",
    "catalog:Permalink"
  ],
  "authors": "Andre Carlucci",
  "catalog:commitId": "fa92c1ba-44bd-4f47-8a2e-37b9e0c38da4",
  "catalog:commitTimeStamp": "2018-11-19T18:32:04.0469621Z",
  "created": "2017-05-23T01:48:24.53Z",
  "description": "Sharp migrations is a framework to help you deal with database changes and versioning over time. The idea comes from the excellent Ruby on Rails migrations and it is the best way to alter your database in a structured and organised manner.",
  "id": "SharpMigrations",
  "isPrerelease": true,
  "lastEdited": "2018-11-19T18:31:39.31Z",
  "licenseUrl": "http://opensource.org/licenses/MIT",
  "listed": true,
  "packageHash": "CW668kVuezhBLXpbqID1Kb2RlOkLy1IHOudC2I2DDDcOOEE4SVHsBRPJ0jjoW+qAMrT7s7u+Kgmdgz7NdXFh/Q==",
  "packageHashAlgorithm": "SHA512",
  "packageSize": 25773,
  "projectUrl": "https://github.com/sharpmigrations/sharpmigrations",
  "published": "2017-05-23T01:48:24.53Z",
  "requireLicenseAcceptance": false,
  "verbatimVersion": "2.0.0-beta3",
  "version": "2.0.0-beta3",
  "dependencyGroups": [
    {
      "@id": "https://api.nuget.org/v3/catalog0/data/2018.11.19.18.32.04/sharpmigrations.2.0.0-beta3.json#dependencygroup/.netstandard1.4",
      "@type": "PackageDependencyGroup",
      "dependencies": [
        {
          "@id": "https://api.nuget.org/v3/catalog0/data/2018.11.19.18.32.04/sharpmigrations.2.0.0-beta3.json#dependencygroup/.netstandard1.4/netstandard.library",
          "@type": "PackageDependency",
          "id": "NETStandard.Library",
          "range": "[1.6.1, )"
        },
        {
          "@id": "https://api.nuget.org/v3/catalog0/data/2018.11.19.18.32.04/sharpmigrations.2.0.0-beta3.json#dependencygroup/.netstandard1.4/sharpdata",
          "@type": "PackageDependency",
          "id": "SharpData",
          "range": "[2.0.0-beta4, )"
        }
      ],
      "targetFramework": ".NETStandard1.4"
    }
  ],
  "packageEntries": [
    {
      "@id": "https://api.nuget.org/v3/catalog0/data/2018.11.19.18.32.04/sharpmigrations.2.0.0-beta3.json#SharpMigrations.nuspec",
      "@type": "PackageEntry",
      "compressedLength": 558,
      "fullName": "SharpMigrations.nuspec",
      "length": 1142,
      "name": "SharpMigrations.nuspec"
    },
    {
      "@id": "https://api.nuget.org/v3/catalog0/data/2018.11.19.18.32.04/sharpmigrations.2.0.0-beta3.json#lib/netstandard1.4/SharpMigrations.dll",
      "@type": "PackageEntry",
      "compressedLength": 13896,
      "fullName": "lib/netstandard1.4/SharpMigrations.dll",
      "length": 31744,
      "name": "SharpMigrations.dll"
    },
    {
      "@id": "https://api.nuget.org/v3/catalog0/data/2018.11.19.18.32.04/sharpmigrations.2.0.0-beta3.json#.signature.p7s",
      "@type": "PackageEntry",
      "compressedLength": 9469,
      "fullName": ".signature.p7s",
      "length": 9469,
      "name": ".signature.p7s"
    }
  ],
  "tags": [
    "migration",
    "migrations",
    "c#",
    "database",
    "database-migrations"
  ],
  "@context": {
    "@vocab": "http://schema.nuget.org/schema#",
    "catalog": "http://schema.nuget.org/catalog#",
    "xsd": "http://www.w3.org/2001/XMLSchema#",
    "dependencies": {
      "@id": "dependency",
      "@container": "@set"
    },
    "dependencyGroups": {
      "@id": "dependencyGroup",
      "@container": "@set"
    },
    "packageEntries": {
      "@id": "packageEntry",
      "@container": "@set"
    },
    "supportedFrameworks": {
      "@id": "supportedFramework",
      "@container": "@set"
    },
    "tags": {
      "@id": "tag",
      "@container": "@set"
    },
    "published": {
      "@type": "xsd:dateTime"
    },
    "created": {
      "@type": "xsd:dateTime"
    },
    "lastEdited": {
      "@type": "xsd:dateTime"
    },
    "catalog:commitTimeStamp": {
      "@type": "xsd:dateTime"
    }
  }
}