{
  "@id": "https://api.nuget.org/v3/catalog0/data/2015.02.05.04.40.41/ncassette.0.0.3.json",
  "@type": [
    "PackageDetails",
    "catalog:Permalink"
  ],
  "authors": "gingray",
  "catalog:commitId": "2778d344-2a6e-402b-a527-dbdae497f2e7",
  "catalog:commitTimeStamp": "2015-02-05T04:40:41.6217146Z",
  "created": "2014-04-12T08:53:50.107Z",
  "description": "NCassette library for helping debug applications with \"heavy\" algorithms",
  "id": "NCassette",
  "isPrerelease": false,
  "language": "en-US",
  "lastEdited": "0001-01-01T00:00:00Z",
  "packageHash": "JE+RGCixzko716lvuOA2RYo3Jp2ifc/CQoXQNjtDOVShiLsVOwbj0chbMoQHWV9WKpFbX4Wk9Cm2L6UAfkG74A==",
  "packageHashAlgorithm": "SHA512",
  "packageSize": 22259,
  "projectUrl": "https://github.com/gingray/NCassette",
  "published": "1900-01-01T00:00:00Z",
  "releaseNotes": "Alpha version",
  "requireLicenseAcceptance": false,
  "title": "NCassette",
  "version": "0.0.3",
  "@context": {
    "@vocab": "http://schema.nuget.org/schema#",
    "catalog": "http://schema.nuget.org/catalog#",
    "xsd": "http://www.w3.org/2001/XMLSchema#",
    "dependencies": {
      "@id": "dependency",
      "@container": "@set"
    },
    "dependencyGroups": {
      "@id": "dependencyGroup",
      "@container": "@set"
    },
    "packageEntries": {
      "@id": "packageEntry",
      "@container": "@set"
    },
    "supportedFrameworks": {
      "@id": "supportedFramework",
      "@container": "@set"
    },
    "tags": {
      "@id": "tag",
      "@container": "@set"
    },
    "published": {
      "@type": "xsd:dateTime"
    },
    "created": {
      "@type": "xsd:dateTime"
    },
    "lastEdited": {
      "@type": "xsd:dateTime"
    },
    "catalog:commitTimeStamp": {
      "@type": "xsd:dateTime"
    }
  }
}