{
  "@id": "https://api.nuget.org/v3/catalog0/data/2019.09.17.05.29.11/baselibrary.fingerpalmznyt.1.0.2.json",
  "@type": [
    "PackageDetails",
    "catalog:Permalink"
  ],
  "authors": "ZX",
  "catalog:commitId": "d007f5f5-fec7-45d8-a9ee-ddcb58116ec3",
  "catalog:commitTimeStamp": "2019-09-17T05:29:11.6513301Z",
  "copyright": "Copyright 2019",
  "created": "2019-09-17T05:24:55.323Z",
  "description": "ZX",
  "iconUrl": "http://icon_url_here_or_delete_this_line/",
  "id": "BaseLibrary.FingerPalmZNYT",
  "isPrerelease": false,
  "lastEdited": "2019-09-17T05:29:04.92Z",
  "licenseUrl": "http://license_url_here_or_delete_this_line/",
  "listed": true,
  "packageHash": "r6VT89GcFQhMJIrKpaedlBMmFG2ata1EEUn6rNSodwbU4Ngq1oTcsQF/ls0wVy0pEwyDjERL7FMeblIQ6YRCsg==",
  "packageHashAlgorithm": "SHA512",
  "packageSize": 809777,
  "projectUrl": "http://project_url_here_or_delete_this_line/",
  "published": "2019-09-17T05:24:55.323Z",
  "releaseNotes": "Summary of changes made in this release of the package.",
  "requireLicenseAcceptance": false,
  "title": "BaseLibrary.FingerPalmZNYT",
  "verbatimVersion": "1.0.2",
  "version": "1.0.2",
  "dependencyGroups": [
    {
      "@id": "https://api.nuget.org/v3/catalog0/data/2019.09.17.05.29.11/baselibrary.fingerpalmznyt.1.0.2.json#dependencygroup",
      "@type": "PackageDependencyGroup",
      "dependencies": [
        {
          "@id": "https://api.nuget.org/v3/catalog0/data/2019.09.17.05.29.11/baselibrary.fingerpalmznyt.1.0.2.json#dependencygroup/baselibrary.classlibrarystand",
          "@type": "PackageDependency",
          "id": "BaseLibrary.ClassLibraryStand",
          "range": "[2.0.55, )"
        }
      ]
    }
  ],
  "packageEntries": [
    {
      "@id": "https://api.nuget.org/v3/catalog0/data/2019.09.17.05.29.11/baselibrary.fingerpalmznyt.1.0.2.json#BaseLibrary.FingerPalmZNYT.nuspec",
      "@type": "PackageEntry",
      "compressedLength": 429,
      "fullName": "BaseLibrary.FingerPalmZNYT.nuspec",
      "length": 920,
      "name": "BaseLibrary.FingerPalmZNYT.nuspec"
    },
    {
      "@id": "https://api.nuget.org/v3/catalog0/data/2019.09.17.05.29.11/baselibrary.fingerpalmznyt.1.0.2.json#lib/net472/BaseLibrary.FingerPalmZNYT.dll",
      "@type": "PackageEntry",
      "compressedLength": 4481,
      "fullName": "lib/net472/BaseLibrary.FingerPalmZNYT.dll",
      "length": 10752,
      "name": "BaseLibrary.FingerPalmZNYT.dll"
    },
    {
      "@id": "https://api.nuget.org/v3/catalog0/data/2019.09.17.05.29.11/baselibrary.fingerpalmznyt.1.0.2.json#content/LocalAuthenticationAPI.dll",
      "@type": "PackageEntry",
      "compressedLength": 15122,
      "fullName": "content/LocalAuthenticationAPI.dll",
      "length": 28160,
      "name": "LocalAuthenticationAPI.dll"
    },
    {
      "@id": "https://api.nuget.org/v3/catalog0/data/2019.09.17.05.29.11/baselibrary.fingerpalmznyt.1.0.2.json#content/LocalAuthenticationAPI2.dll",
      "@type": "PackageEntry",
      "compressedLength": 19383,
      "fullName": "content/LocalAuthenticationAPI2.dll",
      "length": 37376,
      "name": "LocalAuthenticationAPI2.dll"
    },
    {
      "@id": "https://api.nuget.org/v3/catalog0/data/2019.09.17.05.29.11/baselibrary.fingerpalmznyt.1.0.2.json#content/ZniFingerVeinlib.dll",
      "@type": "PackageEntry",
      "compressedLength": 758720,
      "fullName": "content/ZniFingerVeinlib.dll",
      "length": 1588736,
      "name": "ZniFingerVeinlib.dll"
    },
    {
      "@id": "https://api.nuget.org/v3/catalog0/data/2019.09.17.05.29.11/baselibrary.fingerpalmznyt.1.0.2.json#.signature.p7s",
      "@type": "PackageEntry",
      "compressedLength": 9461,
      "fullName": ".signature.p7s",
      "length": 9461,
      "name": ".signature.p7s"
    }
  ],
  "tags": [
    "Tag1",
    "Tag2"
  ],
  "@context": {
    "@vocab": "http://schema.nuget.org/schema#",
    "catalog": "http://schema.nuget.org/catalog#",
    "xsd": "http://www.w3.org/2001/XMLSchema#",
    "dependencies": {
      "@id": "dependency",
      "@container": "@set"
    },
    "dependencyGroups": {
      "@id": "dependencyGroup",
      "@container": "@set"
    },
    "packageEntries": {
      "@id": "packageEntry",
      "@container": "@set"
    },
    "supportedFrameworks": {
      "@id": "supportedFramework",
      "@container": "@set"
    },
    "tags": {
      "@id": "tag",
      "@container": "@set"
    },
    "published": {
      "@type": "xsd:dateTime"
    },
    "created": {
      "@type": "xsd:dateTime"
    },
    "lastEdited": {
      "@type": "xsd:dateTime"
    },
    "catalog:commitTimeStamp": {
      "@type": "xsd:dateTime"
    },
    "reasons": {
      "@container": "@set"
    }
  }
}