{
  "@id": "https://api.nuget.org/v3/catalog0/data/2016.04.19.09.18.53/iugu.net.1.5.5.json",
  "@type": [
    "PackageDetails",
    "catalog:Permalink"
  ],
  "authors": "IUGU",
  "catalog:commitId": "f6e90020-3036-46c0-9a12-c7bffc56f5fb",
  "catalog:commitTimeStamp": "2016-04-19T09:18:53.3989532Z",
  "copyright": "IUGU Copyright ©  2016",
  "created": "2016-04-19T09:18:46.113Z",
  "description": "Client .Net para a API da IUGU",
  "id": "iugu.net",
  "isPrerelease": false,
  "lastEdited": "0001-01-01T00:00:00Z",
  "listed": true,
  "packageHash": "JFsBif8QehBklk9dnfSpq+slZL+qJ5hHcSnIgGFYeGz/YhK2+k7t5xBuGcQ2ZPZ2rKonSBHNQakTTcbpIu/QpA==",
  "packageHashAlgorithm": "SHA512",
  "packageSize": 130182,
  "published": "2016-04-19T09:18:46.113Z",
  "requireLicenseAcceptance": false,
  "title": "iugu.net",
  "verbatimVersion": "1.5.5",
  "version": "1.5.5",
  "dependencyGroups": [
    {
      "@id": "https://api.nuget.org/v3/catalog0/data/2016.04.19.09.18.53/iugu.net.1.5.5.json#dependencygroup",
      "@type": "PackageDependencyGroup",
      "dependencies": [
        {
          "@id": "https://api.nuget.org/v3/catalog0/data/2016.04.19.09.18.53/iugu.net.1.5.5.json#dependencygroup/microsoft.aspnet.webapi.client",
          "@type": "PackageDependency",
          "id": "Microsoft.AspNet.WebApi.Client",
          "range": "[5.2.3, )"
        },
        {
          "@id": "https://api.nuget.org/v3/catalog0/data/2016.04.19.09.18.53/iugu.net.1.5.5.json#dependencygroup/system.net.http.formatting.extension",
          "@type": "PackageDependency",
          "id": "System.Net.Http.Formatting.Extension",
          "range": "[5.2.3, )"
        }
      ]
    }
  ],
  "packageEntries": [
    {
      "@id": "https://api.nuget.org/v3/catalog0/data/2016.04.19.09.18.53/iugu.net.1.5.5.json#iugu.net.nuspec",
      "@type": "PackageEntry",
      "compressedLength": 337,
      "fullName": "iugu.net.nuspec",
      "length": 653,
      "name": "iugu.net.nuspec"
    },
    {
      "@id": "https://api.nuget.org/v3/catalog0/data/2016.04.19.09.18.53/iugu.net.1.5.5.json#lib/net452/iugu.net.dll",
      "@type": "PackageEntry",
      "compressedLength": 55765,
      "fullName": "lib/net452/iugu.net.dll",
      "length": 151040,
      "name": "iugu.net.dll"
    },
    {
      "@id": "https://api.nuget.org/v3/catalog0/data/2016.04.19.09.18.53/iugu.net.1.5.5.json#lib/net452/iugu.net.pdb",
      "@type": "PackageEntry",
      "compressedLength": 71442,
      "fullName": "lib/net452/iugu.net.pdb",
      "length": 359936,
      "name": "iugu.net.pdb"
    }
  ],
  "@context": {
    "@vocab": "http://schema.nuget.org/schema#",
    "catalog": "http://schema.nuget.org/catalog#",
    "xsd": "http://www.w3.org/2001/XMLSchema#",
    "dependencies": {
      "@id": "dependency",
      "@container": "@set"
    },
    "dependencyGroups": {
      "@id": "dependencyGroup",
      "@container": "@set"
    },
    "packageEntries": {
      "@id": "packageEntry",
      "@container": "@set"
    },
    "supportedFrameworks": {
      "@id": "supportedFramework",
      "@container": "@set"
    },
    "tags": {
      "@id": "tag",
      "@container": "@set"
    },
    "published": {
      "@type": "xsd:dateTime"
    },
    "created": {
      "@type": "xsd:dateTime"
    },
    "lastEdited": {
      "@type": "xsd:dateTime"
    },
    "catalog:commitTimeStamp": {
      "@type": "xsd:dateTime"
    }
  }
}