{
  "@id": "https://api.nuget.org/v3/catalog0/data/2019.01.02.12.09.45/scheduledata.1.0.0.json",
  "@type": [
    "PackageDetails",
    "catalog:Permalink"
  ],
  "authors": "ScheduleData",
  "catalog:commitId": "4f35b237-ce24-4acc-b546-e34369f9cedc",
  "catalog:commitTimeStamp": "2019-01-02T12:09:45.7242142Z",
  "created": "2018-02-09T06:53:07.127Z",
  "description": "Package Description",
  "id": "ScheduleData",
  "isPrerelease": false,
  "lastEdited": "2019-01-02T12:09:41.027Z",
  "listed": true,
  "packageHash": "z4yrMZrYgHF10fkeX+1mXsreg3Xi+mUkynEClq5PszXLPPj9J2tMEAeY+cuRI3n2NDF8RsyzRtkFJIeY+Zne9Q==",
  "packageHashAlgorithm": "SHA512",
  "packageSize": 14980,
  "published": "2018-02-09T06:53:07.127Z",
  "requireLicenseAcceptance": false,
  "verbatimVersion": "1.0.0",
  "version": "1.0.0",
  "dependencyGroups": [
    {
      "@id": "https://api.nuget.org/v3/catalog0/data/2019.01.02.12.09.45/scheduledata.1.0.0.json#dependencygroup/.netstandard2.0",
      "@type": "PackageDependencyGroup",
      "dependencies": [
        {
          "@id": "https://api.nuget.org/v3/catalog0/data/2019.01.02.12.09.45/scheduledata.1.0.0.json#dependencygroup/.netstandard2.0/microsoft.entityframeworkcore",
          "@type": "PackageDependency",
          "id": "Microsoft.EntityFrameworkCore",
          "range": "[2.0.1, )"
        }
      ],
      "targetFramework": ".NETStandard2.0"
    }
  ],
  "packageEntries": [
    {
      "@id": "https://api.nuget.org/v3/catalog0/data/2019.01.02.12.09.45/scheduledata.1.0.0.json#ScheduleData.nuspec",
      "@type": "PackageEntry",
      "compressedLength": 325,
      "fullName": "ScheduleData.nuspec",
      "length": 611,
      "name": "ScheduleData.nuspec"
    },
    {
      "@id": "https://api.nuget.org/v3/catalog0/data/2019.01.02.12.09.45/scheduledata.1.0.0.json#lib/netstandard2.0/ScheduleData.dll",
      "@type": "PackageEntry",
      "compressedLength": 3484,
      "fullName": "lib/netstandard2.0/ScheduleData.dll",
      "length": 8704,
      "name": "ScheduleData.dll"
    },
    {
      "@id": "https://api.nuget.org/v3/catalog0/data/2019.01.02.12.09.45/scheduledata.1.0.0.json#.signature.p7s",
      "@type": "PackageEntry",
      "compressedLength": 9466,
      "fullName": ".signature.p7s",
      "length": 9466,
      "name": ".signature.p7s"
    }
  ],
  "@context": {
    "@vocab": "http://schema.nuget.org/schema#",
    "catalog": "http://schema.nuget.org/catalog#",
    "xsd": "http://www.w3.org/2001/XMLSchema#",
    "dependencies": {
      "@id": "dependency",
      "@container": "@set"
    },
    "dependencyGroups": {
      "@id": "dependencyGroup",
      "@container": "@set"
    },
    "packageEntries": {
      "@id": "packageEntry",
      "@container": "@set"
    },
    "supportedFrameworks": {
      "@id": "supportedFramework",
      "@container": "@set"
    },
    "tags": {
      "@id": "tag",
      "@container": "@set"
    },
    "published": {
      "@type": "xsd:dateTime"
    },
    "created": {
      "@type": "xsd:dateTime"
    },
    "lastEdited": {
      "@type": "xsd:dateTime"
    },
    "catalog:commitTimeStamp": {
      "@type": "xsd:dateTime"
    }
  }
}