{
  "@id": "https://api.nuget.org/v3/catalog0/data/2019.03.28.16.38.35/dap.local.0.6.8.json",
  "@type": [
    "PackageDetails",
    "catalog:Permalink"
  ],
  "authors": "YJ Park",
  "catalog:commitId": "615c682c-5179-42fa-99ee-a7f6b370f816",
  "catalog:commitTimeStamp": "2019-03-28T16:38:35.8494924Z",
  "created": "2019-03-28T16:34:16.727Z",
  "description": "Local Libs",
  "id": "Dap.Local",
  "isPrerelease": false,
  "lastEdited": "2019-03-28T16:38:29.443Z",
  "listed": true,
  "packageHash": "n1PiWRfrzm0ZfObPue+8IAocMnJ7lDk7bUAH5xp/9CUM044gVn5Y4sFjH5HB1zNG4r4dyL+GjF6gigKCpcpzEg==",
  "packageHashAlgorithm": "SHA512",
  "packageSize": 66216,
  "projectUrl": "https://github.com/yjpark/dap.lib.fsharp",
  "published": "2019-03-28T16:34:16.727Z",
  "releaseNotes": "put IEnvironment.Instance into Helper.fs",
  "requireLicenseAcceptance": false,
  "verbatimVersion": "0.6.8",
  "version": "0.6.8",
  "dependencyGroups": [
    {
      "@id": "https://api.nuget.org/v3/catalog0/data/2019.03.28.16.38.35/dap.local.0.6.8.json#dependencygroup/.netstandard2.0",
      "@type": "PackageDependencyGroup",
      "dependencies": [
        {
          "@id": "https://api.nuget.org/v3/catalog0/data/2019.03.28.16.38.35/dap.local.0.6.8.json#dependencygroup/.netstandard2.0/dap.archive",
          "@type": "PackageDependency",
          "id": "Dap.Archive",
          "range": "[0.6.0, )"
        }
      ],
      "targetFramework": ".NETStandard2.0"
    }
  ],
  "packageEntries": [
    {
      "@id": "https://api.nuget.org/v3/catalog0/data/2019.03.28.16.38.35/dap.local.0.6.8.json#Dap.Local.nuspec",
      "@type": "PackageEntry",
      "compressedLength": 423,
      "fullName": "Dap.Local.nuspec",
      "length": 728,
      "name": "Dap.Local.nuspec"
    },
    {
      "@id": "https://api.nuget.org/v3/catalog0/data/2019.03.28.16.38.35/dap.local.0.6.8.json#lib/netstandard2.0/Dap.Local.dll",
      "@type": "PackageEntry",
      "compressedLength": 54653,
      "fullName": "lib/netstandard2.0/Dap.Local.dll",
      "length": 147456,
      "name": "Dap.Local.dll"
    },
    {
      "@id": "https://api.nuget.org/v3/catalog0/data/2019.03.28.16.38.35/dap.local.0.6.8.json#.signature.p7s",
      "@type": "PackageEntry",
      "compressedLength": 9463,
      "fullName": ".signature.p7s",
      "length": 9463,
      "name": ".signature.p7s"
    }
  ],
  "tags": [
    "fsharp",
    "dap"
  ],
  "@context": {
    "@vocab": "http://schema.nuget.org/schema#",
    "catalog": "http://schema.nuget.org/catalog#",
    "xsd": "http://www.w3.org/2001/XMLSchema#",
    "dependencies": {
      "@id": "dependency",
      "@container": "@set"
    },
    "dependencyGroups": {
      "@id": "dependencyGroup",
      "@container": "@set"
    },
    "packageEntries": {
      "@id": "packageEntry",
      "@container": "@set"
    },
    "supportedFrameworks": {
      "@id": "supportedFramework",
      "@container": "@set"
    },
    "tags": {
      "@id": "tag",
      "@container": "@set"
    },
    "published": {
      "@type": "xsd:dateTime"
    },
    "created": {
      "@type": "xsd:dateTime"
    },
    "lastEdited": {
      "@type": "xsd:dateTime"
    },
    "catalog:commitTimeStamp": {
      "@type": "xsd:dateTime"
    }
  }
}