{
  "@id": "https://api.nuget.org/v3/catalog0/data/2015.02.02.02.33.18/hyprlinkr.0.3.1.json",
  "@type": [
    "PackageDetails",
    "catalog:Permalink"
  ],
  "authors": "Mark Seemann",
  "catalog:commitId": "517fd862-e544-4024-b812-95bda3caf9c7",
  "catalog:commitTimeStamp": "2015-02-02T02:33:18.1871488Z",
  "copyright": "Copyright Mark Seemann 2012",
  "created": "2012-08-16T20:32:51.1Z",
  "description": "Hyprlinkr is a small and very focused helper library for the ASP.NET Web API. It does one thing only: it creates URIs according to the application's route configuration in a type-safe manner.",
  "id": "Hyprlinkr",
  "isPrerelease": false,
  "lastEdited": "0001-01-01T00:00:00Z",
  "packageHash": "1vUBQfhA8HQ4eeWdcw48uNAUYdbobDXZazps6iWufif8hkXO7OhXXoeGVZjYX3+nJllIGRVLt6/lAF9OJU0dug==",
  "packageHashAlgorithm": "SHA512",
  "packageSize": 12504,
  "projectUrl": "https://github.com/ploeh/Hyprlinkr",
  "published": "2012-08-16T20:32:56.63Z",
  "requireLicenseAcceptance": false,
  "title": "Hyprlinkr",
  "version": "0.3.1",
  "dependencyGroups": [
    {
      "@id": "https://api.nuget.org/v3/catalog0/data/2015.02.02.02.33.18/hyprlinkr.0.3.1.json#dependencygroup",
      "@type": "PackageDependencyGroup",
      "dependencies": [
        {
          "@id": "https://api.nuget.org/v3/catalog0/data/2015.02.02.02.33.18/hyprlinkr.0.3.1.json#dependencygroup/aspnetwebapi.core",
          "@type": "PackageDependency",
          "id": "AspNetWebApi.Core",
          "range": "[4.0.20710, )"
        }
      ]
    }
  ],
  "@context": {
    "@vocab": "http://schema.nuget.org/schema#",
    "catalog": "http://schema.nuget.org/catalog#",
    "xsd": "http://www.w3.org/2001/XMLSchema#",
    "dependencies": {
      "@id": "dependency",
      "@container": "@set"
    },
    "dependencyGroups": {
      "@id": "dependencyGroup",
      "@container": "@set"
    },
    "packageEntries": {
      "@id": "packageEntry",
      "@container": "@set"
    },
    "supportedFrameworks": {
      "@id": "supportedFramework",
      "@container": "@set"
    },
    "tags": {
      "@id": "tag",
      "@container": "@set"
    },
    "published": {
      "@type": "xsd:dateTime"
    },
    "created": {
      "@type": "xsd:dateTime"
    },
    "lastEdited": {
      "@type": "xsd:dateTime"
    },
    "catalog:commitTimeStamp": {
      "@type": "xsd:dateTime"
    }
  }
}