{
  "@id": "https://api.nuget.org/v3/catalog0/data/2018.12.05.07.00.01/laurus.uitest.1.0.15.json",
  "@type": [
    "PackageDetails",
    "catalog:Permalink"
  ],
  "authors": "ngamroth",
  "catalog:commitId": "345a365b-1188-46f3-816e-54fc6a99c7b9",
  "catalog:commitTimeStamp": "2018-12-05T07:00:01.9514653Z",
  "copyright": "Copyright 2013",
  "created": "2014-01-30T03:04:03.16Z",
  "description": "Page builder UI test metaframework",
  "id": "Laurus.UiTest",
  "isPrerelease": false,
  "lastEdited": "2018-12-05T06:59:23.073Z",
  "listed": true,
  "packageHash": "qsvzfMo+I8GCPAiFOaJBPN++JZwBt/4QoHGr8y609fildm+TazQVGa3y9E5SxhUJCsCgUnlrSjmCnJAPfo2WDw==",
  "packageHashAlgorithm": "SHA512",
  "packageSize": 16608,
  "projectUrl": "https://github.com/thebeekeeper/Laurus.UiTest",
  "published": "2014-01-30T03:04:03.16Z",
  "releaseNotes": "Pre-beta release",
  "requireLicenseAcceptance": false,
  "title": "Laurus UiTest",
  "verbatimVersion": "1.0.15",
  "version": "1.0.15",
  "dependencyGroups": [
    {
      "@id": "https://api.nuget.org/v3/catalog0/data/2018.12.05.07.00.01/laurus.uitest.1.0.15.json#dependencygroup",
      "@type": "PackageDependencyGroup",
      "dependencies": [
        {
          "@id": "https://api.nuget.org/v3/catalog0/data/2018.12.05.07.00.01/laurus.uitest.1.0.15.json#dependencygroup/castle.windsor",
          "@type": "PackageDependency",
          "id": "Castle.Windsor",
          "range": "[3.2.0, )"
        }
      ]
    }
  ],
  "packageEntries": [
    {
      "@id": "https://api.nuget.org/v3/catalog0/data/2018.12.05.07.00.01/laurus.uitest.1.0.15.json#Laurus.UiTest.nuspec",
      "@type": "PackageEntry",
      "compressedLength": 374,
      "fullName": "Laurus.UiTest.nuspec",
      "length": 736,
      "name": "Laurus.UiTest.nuspec"
    },
    {
      "@id": "https://api.nuget.org/v3/catalog0/data/2018.12.05.07.00.01/laurus.uitest.1.0.15.json#lib/net40/Laurus.UiTest.dll",
      "@type": "PackageEntry",
      "compressedLength": 4322,
      "fullName": "lib/net40/Laurus.UiTest.dll",
      "length": 9728,
      "name": "Laurus.UiTest.dll"
    },
    {
      "@id": "https://api.nuget.org/v3/catalog0/data/2018.12.05.07.00.01/laurus.uitest.1.0.15.json#.signature.p7s",
      "@type": "PackageEntry",
      "compressedLength": 9465,
      "fullName": ".signature.p7s",
      "length": 9465,
      "name": ".signature.p7s"
    }
  ],
  "tags": [
    "Testing",
    "UI",
    "Automation"
  ],
  "@context": {
    "@vocab": "http://schema.nuget.org/schema#",
    "catalog": "http://schema.nuget.org/catalog#",
    "xsd": "http://www.w3.org/2001/XMLSchema#",
    "dependencies": {
      "@id": "dependency",
      "@container": "@set"
    },
    "dependencyGroups": {
      "@id": "dependencyGroup",
      "@container": "@set"
    },
    "packageEntries": {
      "@id": "packageEntry",
      "@container": "@set"
    },
    "supportedFrameworks": {
      "@id": "supportedFramework",
      "@container": "@set"
    },
    "tags": {
      "@id": "tag",
      "@container": "@set"
    },
    "published": {
      "@type": "xsd:dateTime"
    },
    "created": {
      "@type": "xsd:dateTime"
    },
    "lastEdited": {
      "@type": "xsd:dateTime"
    },
    "catalog:commitTimeStamp": {
      "@type": "xsd:dateTime"
    }
  }
}