{
  "@id": "https://api.nuget.org/v3/catalog0/data/2018.12.07.15.59.40/matrixden.lightdb.dll.1.0.1.json",
  "@type": [
    "PackageDetails",
    "catalog:Permalink"
  ],
  "authors": "Lionden",
  "catalog:commitId": "cb92c113-7345-4791-a799-f086269650af",
  "catalog:commitTimeStamp": "2018-12-07T15:59:40.3307869Z",
  "copyright": "Copyright 2017",
  "created": "2017-05-07T13:24:14.853Z",
  "description": "A common SQL helper.",
  "iconUrl": "http://tva4.sinaimg.cn/crop.0.0.239.239.180/89e13697tw1ek7gu0ax15j206o06ojs1.jpg",
  "id": "Matrixden.LightDB.dll",
  "isPrerelease": false,
  "lastEdited": "2018-12-07T15:59:21.03Z",
  "licenseUrl": "http://www.cnblogs.com/lionden/",
  "listed": true,
  "packageHash": "sjKfZnyCifwZ79j4uWrotVzMO9c2R82K5/Fj0YsBGRwJq5WcP+WJUAOo50qDJHju5yk1svJMjbeeb6DPb7Holw==",
  "packageHashAlgorithm": "SHA512",
  "packageSize": 213384,
  "projectUrl": "http://www.cnblogs.com/lionden/",
  "published": "2017-05-07T13:24:14.853Z",
  "releaseNotes": "Summary of changes made in this release of the package.",
  "requireLicenseAcceptance": false,
  "verbatimVersion": "1.0.1",
  "version": "1.0.1",
  "dependencyGroups": [
    {
      "@id": "https://api.nuget.org/v3/catalog0/data/2018.12.07.15.59.40/matrixden.lightdb.dll.1.0.1.json#dependencygroup",
      "@type": "PackageDependencyGroup",
      "dependencies": [
        {
          "@id": "https://api.nuget.org/v3/catalog0/data/2018.12.07.15.59.40/matrixden.lightdb.dll.1.0.1.json#dependencygroup/mysql.data",
          "@type": "PackageDependency",
          "id": "MySql.Data",
          "range": "[6.9.0, )"
        }
      ]
    }
  ],
  "packageEntries": [
    {
      "@id": "https://api.nuget.org/v3/catalog0/data/2018.12.07.15.59.40/matrixden.lightdb.dll.1.0.1.json#Matrixden.LightDB.dll.nuspec",
      "@type": "PackageEntry",
      "compressedLength": 463,
      "fullName": "Matrixden.LightDB.dll.nuspec",
      "length": 889,
      "name": "Matrixden.LightDB.dll.nuspec"
    },
    {
      "@id": "https://api.nuget.org/v3/catalog0/data/2018.12.07.15.59.40/matrixden.lightdb.dll.1.0.1.json#Matrixden.LightDB.dll",
      "@type": "PackageEntry",
      "compressedLength": 12454,
      "fullName": "Matrixden.LightDB.dll",
      "length": 30720,
      "name": "Matrixden.LightDB.dll"
    },
    {
      "@id": "https://api.nuget.org/v3/catalog0/data/2018.12.07.15.59.40/matrixden.lightdb.dll.1.0.1.json#Matrixden.LightDB.pdb",
      "@type": "PackageEntry",
      "compressedLength": 16867,
      "fullName": "Matrixden.LightDB.pdb",
      "length": 71168,
      "name": "Matrixden.LightDB.pdb"
    },
    {
      "@id": "https://api.nuget.org/v3/catalog0/data/2018.12.07.15.59.40/matrixden.lightdb.dll.1.0.1.json#MySql.Data.dll",
      "@type": "PackageEntry",
      "compressedLength": 172193,
      "fullName": "MySql.Data.dll",
      "length": 424448,
      "name": "MySql.Data.dll"
    },
    {
      "@id": "https://api.nuget.org/v3/catalog0/data/2018.12.07.15.59.40/matrixden.lightdb.dll.1.0.1.json#.signature.p7s",
      "@type": "PackageEntry",
      "compressedLength": 9463,
      "fullName": ".signature.p7s",
      "length": 9463,
      "name": ".signature.p7s"
    }
  ],
  "tags": [
    "SQL",
    "MySQL"
  ],
  "@context": {
    "@vocab": "http://schema.nuget.org/schema#",
    "catalog": "http://schema.nuget.org/catalog#",
    "xsd": "http://www.w3.org/2001/XMLSchema#",
    "dependencies": {
      "@id": "dependency",
      "@container": "@set"
    },
    "dependencyGroups": {
      "@id": "dependencyGroup",
      "@container": "@set"
    },
    "packageEntries": {
      "@id": "packageEntry",
      "@container": "@set"
    },
    "supportedFrameworks": {
      "@id": "supportedFramework",
      "@container": "@set"
    },
    "tags": {
      "@id": "tag",
      "@container": "@set"
    },
    "published": {
      "@type": "xsd:dateTime"
    },
    "created": {
      "@type": "xsd:dateTime"
    },
    "lastEdited": {
      "@type": "xsd:dateTime"
    },
    "catalog:commitTimeStamp": {
      "@type": "xsd:dateTime"
    }
  }
}