{
  "@id": "https://api.nuget.org/v3/catalog0/data/2018.12.10.14.47.30/azuredataeaseofuse.0.1.0-beta.json",
  "@type": [
    "PackageDetails",
    "catalog:Permalink"
  ],
  "authors": "Randy Skopecek",
  "catalog:commitId": "00b08955-16d5-4d30-ad60-aa0fb78ca510",
  "catalog:commitTimeStamp": "2018-12-10T14:47:30.054839Z",
  "copyright": "Randy Skopecek 2014",
  "created": "2014-02-07T01:55:44.31Z",
  "description": "Less code for Azure Storage and Caching. MIT Licensed.",
  "id": "AzureDataEaseOfUse",
  "isPrerelease": true,
  "lastEdited": "2018-12-10T14:47:04.547Z",
  "licenseUrl": "https://github.com/WindowsAzure-Contrib/AzureDataEaseOfUse/blob/master/LICENSE",
  "listed": true,
  "packageHash": "7gbN4civLW0C6u1CQabKQuKJoNrEYVw6/CNUXJk4xkqYkoBAfgjj0C/0UaMSjK+fLWt2kANuxtD48/8Om8AWEA==",
  "packageHashAlgorithm": "SHA512",
  "packageSize": 17652,
  "projectUrl": "https://github.com/WindowsAzure-Contrib/AzureDataEaseOfUse",
  "published": "2014-02-07T01:55:44.31Z",
  "releaseNotes": "Table crud, search, and batch added",
  "requireLicenseAcceptance": false,
  "title": "Azure Data Ease Of Use",
  "verbatimVersion": "0.1.0-beta",
  "version": "0.1.0-beta",
  "dependencyGroups": [
    {
      "@id": "https://api.nuget.org/v3/catalog0/data/2018.12.10.14.47.30/azuredataeaseofuse.0.1.0-beta.json#dependencygroup",
      "@type": "PackageDependencyGroup",
      "dependencies": [
        {
          "@id": "https://api.nuget.org/v3/catalog0/data/2018.12.10.14.47.30/azuredataeaseofuse.0.1.0-beta.json#dependencygroup/windowsazure.storage",
          "@type": "PackageDependency",
          "id": "WindowsAzure.Storage",
          "range": "[3.0.2, )"
        }
      ]
    }
  ],
  "packageEntries": [
    {
      "@id": "https://api.nuget.org/v3/catalog0/data/2018.12.10.14.47.30/azuredataeaseofuse.0.1.0-beta.json#AzureDataEaseOfUse.nuspec",
      "@type": "PackageEntry",
      "compressedLength": 445,
      "fullName": "AzureDataEaseOfUse.nuspec",
      "length": 919,
      "name": "AzureDataEaseOfUse.nuspec"
    },
    {
      "@id": "https://api.nuget.org/v3/catalog0/data/2018.12.10.14.47.30/azuredataeaseofuse.0.1.0-beta.json#lib/net45/AzureDataEaseOfUse.dll",
      "@type": "PackageEntry",
      "compressedLength": 5095,
      "fullName": "lib/net45/AzureDataEaseOfUse.dll",
      "length": 11264,
      "name": "AzureDataEaseOfUse.dll"
    },
    {
      "@id": "https://api.nuget.org/v3/catalog0/data/2018.12.10.14.47.30/azuredataeaseofuse.0.1.0-beta.json#.signature.p7s",
      "@type": "PackageEntry",
      "compressedLength": 9465,
      "fullName": ".signature.p7s",
      "length": 9465,
      "name": ".signature.p7s"
    }
  ],
  "tags": [
    "Azure"
  ],
  "@context": {
    "@vocab": "http://schema.nuget.org/schema#",
    "catalog": "http://schema.nuget.org/catalog#",
    "xsd": "http://www.w3.org/2001/XMLSchema#",
    "dependencies": {
      "@id": "dependency",
      "@container": "@set"
    },
    "dependencyGroups": {
      "@id": "dependencyGroup",
      "@container": "@set"
    },
    "packageEntries": {
      "@id": "packageEntry",
      "@container": "@set"
    },
    "supportedFrameworks": {
      "@id": "supportedFramework",
      "@container": "@set"
    },
    "tags": {
      "@id": "tag",
      "@container": "@set"
    },
    "published": {
      "@type": "xsd:dateTime"
    },
    "created": {
      "@type": "xsd:dateTime"
    },
    "lastEdited": {
      "@type": "xsd:dateTime"
    },
    "catalog:commitTimeStamp": {
      "@type": "xsd:dateTime"
    }
  }
}